wealths-0.0.3.dist-info/METADATA
wealths-0.0.3.dist-info/WHEEL
wealths.libs/libgcc_s-1e52349c.so.1
wealths.libs/libstdc++-e3b7606c.so.6
wealths/wealths.pyi
wealths/__init__.py
wealths/wealths.cpython-39-x86_64-linux-gnu.so
wealths-0.0.3.dist-info/RECORD
